{
  "version": 1,
  "append_index_after_first": true,
  "marker": "TABLE_LABEL",
  "rules": [
    {
      "label": "Acceptance Test crap",
      "priority": 1000,
      "must_contain_all": ["Foo"],
      "must_contain_any": [],

      
      "must_not_contain": [],
      "min_rows": 3,
      "min_cols": 3,
      "max_rows": 0,
      "max_cols": 0,
      "match_scope": "any_cell"
    },
    {
      "label": "Acceptance Test InformationZ",
      "priority": 1000,
      "must_contain_all": ["resistance", "voltage", "test temp", "valve voltage", "kohm"],
      "must_contain_any": [],
      "must_not_contain": [],
      "min_rows": 3,
      "min_cols": 3,
      "max_rows": 0,
      "max_cols": 0,
      "match_scope": "any_cell"
    }
  ]
}
